Metadata-Version: 1.0
Name: StockTrader
Version: 1.1
Summary: It helps one know the value of their stock
Home-page: https://github.com/madhuradlakha/Stock-Trading-API/blob/master/stock.py
Author: Madhur Adlakha
Author-email: madhuradlakha@yahoo.co.in
License: MIT
Platform: UNKNOWN
